discordsdk/__init__.py
discordsdk/abc.py
discordsdk/ac.py
discordsdk/client.py
discordsdk/context.py
discordsdk/embed.py
discordsdk/events.py
discordsdk/exceptions.py
discordsdk/gateway.py
discordsdk/http.py
discordsdk/message.py
discordsdk/parsers.py
discordsdk/state.py
discordsdk/types.py
discordsdk/utils.py
discordsdk/webhooks.py
discord_sdk-0.1.2a0.dist-info/METADATA
discord_sdk-0.1.2a0.dist-info/WHEEL
discord_sdk-0.1.2a0.dist-info/top_level.txt
discord_sdk-0.1.2a0.dist-info/RECORD
